no_version/__init__.py
no_version-0.1.0.dist-info/LICENSE
no_version-0.1.0.dist-info/METADATA
no_version-0.1.0.dist-info/WHEEL
no_version-0.1.0.dist-info/top_level.txt
no_version-0.1.0.dist-info/RECORD
